MANIFEST.in
account_chart.xml
account_chart_assoc.xml
account_chart_pymes.xml
fiscal_templates.xml
fiscal_templates_assoc.xml
fiscal_templates_pymes.xml
l10n_es_wizard.xml
setup.py
taxes_data.xml
taxes_data_assoc.xml
taxes_data_pymes.xml
./__init__.py
./__openerp__.py
i18n/ar.po
i18n/ca.po
i18n/da.po
i18n/de.po
i18n/es.po
i18n/es_CR.po
i18n/es_MX.po
i18n/es_PY.po
i18n/es_VE.po
i18n/fr.po
i18n/gl.po
i18n/hu.po
i18n/it.po
i18n/l10n_es.pot
i18n/nl.po
i18n/oc.po
i18n/pt.po
i18n/pt_BR.po
i18n/sl.po
i18n/sr@latin.po
i18n/tr.po
images/config_chart_l10n_es.jpeg
images/l10n_es_chart.jpeg
openerp_l10n_es.egg-info/PKG-INFO
openerp_l10n_es.egg-info/SOURCES.txt
openerp_l10n_es.egg-info/dependency_links.txt
openerp_l10n_es.egg-info/requires.txt
openerp_l10n_es.egg-info/top_level.txt
static/src/img/icon.png